torch_ga/__init__.py
torch_ga/__version__.py
torch_ga/blades.py
torch_ga/cayley.py
torch_ga/jacobian.py
torch_ga/layers.py
torch_ga/mv.py
torch_ga/mv_ops.py
torch_ga/plots.py
torch_ga/torch_ga.py
torch_ga/transform.py
torch_ga/utils.py
torch_ga-0.0.5.dist-info/licenses/LICENSE
torch_ga-0.0.5.dist-info/METADATA
torch_ga-0.0.5.dist-info/WHEEL
torch_ga-0.0.5.dist-info/top_level.txt
torch_ga-0.0.5.dist-info/RECORD
