Metadata-Version: 2.4
Name: torch_ga
Version: 0.0.5
Summary: Clifford and Geometric Algebra with PyTorch
Home-page: https://github.com/falesiani/torch_ga
Author: Francesco Alesiani
Author-email: Francesco Alesiani <francesco.alesiani@neclab.eu>
License: MIT
Project-URL: Homepage, https://github.com/falesiani/torch_ga
Project-URL: Repository, https://github.com/falesiani/torch_ga.git
Keywords: geometric-algebra,clifford-algebra,pytorch,multi-vector,para-vector,mathematics,machine-learning
Classifier: License :: OSI Approved :: MIT License
Classifier: Development Status :: 3 - Alpha
Classifier: Programming Language :: Python :: 3
Classifier: Intended Audience :: Education
Classifier: Intended Audience :: Developers
Classifier: Intended Audience :: Science/Research
Classifier: Topic :: Scientific/Engineering
Classifier: Topic :: Scientific/Engineering :: Physics
Classifier: Topic :: Scientific/Engineering :: Mathematics
Classifier: Topic :: Scientific/Engineering :: Artificial Intelligence
Classifier: Topic :: Software Development
Classifier: Topic :: Software Development :: Libraries
Classifier: Topic :: Software Development :: Libraries :: Python Modules
Requires-Python: >=3.7
License-File: LICENSE
Provides-Extra: torch
Requires-Dist: pytorch>=1.12.1; extra == "torch"
Dynamic: author
Dynamic: home-page
Dynamic: license-file
